pyqzone/__init__.py
pyqzone/api/__init__.py
pyqzone/api/model.py
pyqzone/api/web/__init__.py
pyqzone/api/web/album.py
pyqzone/api/web/blog.py
pyqzone/api/web/board.py
pyqzone/api/web/emotion.py
pyqzone/api/web/friend.py
pyqzone/api/web/host.py
pyqzone/api/web/profile.py
pyqzone/client/__init__.py
pyqzone/client/model.py
pyqzone/client/web/__init__.py
pyqzone/client/web/host.py
pyqzone/entities/__init__.py
pyqzone/entities/emotion.py
pyqzone/entities/friend.py
pyqzone/entities/misc.py
pyqzone/protocol/__init__.py
pyqzone/utils/__init__.py
pyqzone-0.0.0.1.dist-info/METADATA
pyqzone-0.0.0.1.dist-info/WHEEL
pyqzone-0.0.0.1.dist-info/licenses/LICENSE
pyqzone-0.0.0.1.dist-info/RECORD
