Metadata-Version: 2.1
Name: pyqzone
Version: 0.0.0.1
Summary: QQ空间协议封装
Project-URL: Homepage, https://github.com/tttux/pyqzone
Project-URL: Bug Tracker, https://github.com/tttux/pyqzone/issues
Author-email: Tu Xuan <tttuxan@outlook.com>
License:                     GNU AFFERO GENERAL PUBLIC LICENSE
License-File: LICENSE
Classifier: License :: OSI Approved :: GNU Affero General Public License v3
Classifier: Operating System :: OS Independent
Classifier: Programming Language :: Python :: 3
Requires-Python: >=3.7
Requires-Dist: requests
